davdovin_poetry_package/__init__.py
davdovin_poetry_package/package.py
davdovin_poetry_package-0.1.0.dist-info/METADATA
davdovin_poetry_package-0.1.0.dist-info/WHEEL
davdovin_poetry_package-0.1.0.dist-info/RECORD
