Metadata-Version: 2.3
Name: davdovin-poetry-package
Version: 0.1.0
Summary: learn how to build a python package with poetry
Author: Danil Vdovin
Author-email: felixffox@yandex.ru
Requires-Python: >=3.11
Classifier: Programming Language :: Python :: 3
Classifier: Programming Language :: Python :: 3.11
Classifier: Programming Language :: Python :: 3.12
Classifier: Programming Language :: Python :: 3.13
